LICENSE
MANIFEST.in
README.md
setup.py
python_la/BaseClasses.py
python_la/__init__.py
python_la.egg-info/PKG-INFO
python_la.egg-info/SOURCES.txt
python_la.egg-info/dependency_links.txt
python_la.egg-info/requires.txt
python_la.egg-info/top_level.txt
python_la/la1/Complex.py
python_la/la1/LinearMap.py
python_la/la1/Matrix.py
python_la/la1/Span.py
python_la/la1/Vector.py
python_la/la1/__init__.py
python_la/la1/Field/ComplexField.py
python_la/la1/Field/Field.py
python_la/la1/Field/RationalField.py
python_la/la1/Field/RealField.py
python_la/la1/Field/__init__.py
python_la/la1/VectorSpace/VectorSpace.py
python_la/la1/VectorSpace/__init__.py
python_la/la2/BilinearForm.py
python_la/la2/InnerProduct.py
python_la/la2/InnerProductSpace.py
python_la/la2/__init__.py
python_la/la2/Calculable/Calculable.py
python_la/la2/Calculable/Expression.py
python_la/la2/Calculable/Polynomial.py
python_la/la2/Calculable/PolynomialCompact.py
python_la/la2/Calculable/PolynomialFraction.py
python_la/la2/Calculable/PolynomialSimple.py
python_la/la2/Calculable/__init__.py
python_la/utils/__init__.py
python_la/utils/decorators/__init__.py
python_la/utils/decorators/class_decorators.py
python_la/utils/decorators/memory.py
python_la/utils/decorators/other.py
python_la/utils/helpers/__init__.py
python_la/utils/helpers/helpers.py
python_la/utils/helpers/instance_cheking.py
python_la/utils/helpers/math_symbols.py
python_la/utils/helpers/mathematical_helpers.py
python_la/utils/helpers/polynomial_from_string_helper_functions.py
python_la/utils/helpers/pretty_print.py
python_la/utils/helpers/string_manipulation.py