Metadata-Version: 2.1
Name: python-la
Version: 0.97.0
Summary: Python linear algebra liabrary
Home-page: UNKNOWN
Author: danielnachumdev (Daniel Nachum)
Author-email: <danielnachumdev@gmail.com>
License: UNKNOWN
Keywords: python,linear algebra,vector,matrix,field,vector field,span,linear maps,bilinear form,inner product,linear transformation
Platform: UNKNOWN
Classifier: Intended Audience :: Developers
Classifier: Programming Language :: Python :: 3
Classifier: Operating System :: Unix
Classifier: Operating System :: MacOS :: MacOS X
Classifier: Operating System :: Microsoft :: Windows
License-File: LICENSE
